Metadata-Version: 2.1
Name: sense-core
Version: 0.2.93
Summary: sense core
Home-page: 
Author: kafka0102
Author-email: yujianjia@sensedeal.ai
License: BSD License
Classifier: Environment :: Web Environment
Classifier: Framework :: Django
Classifier: Framework :: Django :: 2.1
Classifier: Intended Audience :: Developers
Classifier: License :: OSI Approved :: BSD License
Classifier: Operating System :: OS Independent
Classifier: Programming Language :: Python
Classifier: Programming Language :: Python :: 3.7
Classifier: Programming Language :: Python :: 3.8
Classifier: Topic :: Internet :: WWW/HTTP
Classifier: Topic :: Internet :: WWW/HTTP :: Dynamic Content
Requires-Dist: pymongo (>=3.7)
Requires-Dist: python-decouple (>=3.1)
Requires-Dist: redis
Requires-Dist: pycrypto (==2.6.1)
Requires-Dist: pymysql
Requires-Dist: elasticsearch-dsl (==6.3.1)
Requires-Dist: pika (>=1.1.0)
Requires-Dist: shortuuid
Requires-Dist: requests
Requires-Dist: threadpool (>=1.3.2)
Requires-Dist: python-dateutil (>=2.7)
Requires-Dist: sqlalchemy (>=1.2)
